michell/__init__.py
michell/raytracer.py
michell/scene.py
michell/textures.py
michell/utils.py
michell_raytracer-0.0.3.dist-info/LICENSE
michell_raytracer-0.0.3.dist-info/METADATA
michell_raytracer-0.0.3.dist-info/WHEEL
michell_raytracer-0.0.3.dist-info/top_level.txt
michell_raytracer-0.0.3.dist-info/RECORD
