Metadata-Version: 2.1
Name: michell-raytracer
Version: 0.0.3
Summary: Relativistic non-linear raytracer for Schwarzschild's metric.
Home-page: https://github.com/viktor-akusov/michell-raytracer
Author: Viktor Akusov
Author-email: viktor@akusov.xyz
License: MIT
Project-URL: Bug Tracker, https://github.com/viktor-akusov/michell-raytracer/issues
Keywords: raytracer,black hole,nonlinear
Classifier: Programming Language :: Python :: 3
Classifier: License :: OSI Approved :: MIT License
Classifier: Operating System :: OS Independent
Requires-Python: >=3.6
License-File: LICENSE
Requires-Dist: numpy (>=1.22.4)
Requires-Dist: Pillow (>=9.1.1)
Requires-Dist: progressbar (>=2.5)
